{
  "project_info": {
    "project_number": "729837592914",
    "project_id": "homework4-97004",
    "storage_bucket": "homework4-97004.firebasestorage.app"
  },
  "client": [
    {
      "client_info": {
        "mobilesdk_app_id": "1:729837592914:android:d557f9bb41855888c69a8b",
        "android_client_info": {
          "package_name": "com.example.homework4"
        }
      },
      "oauth_client": [],
      "api_key": [
        {
          "current_key": "AIzaSyD-yqjcwCv8pmFBSqF5avN-0jZ3t5KMEVc"
        }
      ],
      "services": {
        "appinvite_service": {
          "other_platform_oauth_client": []
        }
      }
    },
    {
      "client_info": {
        "mobilesdk_app_id": "1:729837592914:android:94dde4336436ede4c69a8b",
        "android_client_info": {
          "package_name": "com.example.hw4"
        }
      },
      "oauth_client": [],
      "api_key": [
        {
          "current_key": "AIzaSyD-yqjcwCv8pmFBSqF5avN-0jZ3t5KMEVc"
        }
      ],
      "services": {
        "appinvite_service": {
          "other_platform_oauth_client": []
        }
      }
    },
    {
      "client_info": {
        "mobilesdk_app_id": "1:729837592914:android:2cb43c8e20da3ee6c69a8b",
        "android_client_info": {
          "package_name": "com.example.msgapp"
        }
      },
      "oauth_client": [],
      "api_key": [
        {
          "current_key": "AIzaSyD-yqjcwCv8pmFBSqF5avN-0jZ3t5KMEVc"
        }
      ],
      "services": {
        "appinvite_service": {
          "other_platform_oauth_client": []
        }
      }
    }
  ],
  "configuration_version": "1"
}